{
    "SIGAA_REGISTRATION": {
        "step": "sigaaRegistration",
        "position": 1,
        "description": "Matricula"
    },
    "DOCUMENTATION": {
        "step": "documentation",
        "position": 2,
        "description": "Documentação"
    },
    "INTERNSHIP_PLAN": {
        "step": "internshipPlan",
        "position": 3,
        "description": "Plano de Estágio"
    },
    "PERFORMANCE_EVALUATION": {
        "step": "performanceEvaluation",
        "position": 4,
        "description": "Avaliação de Desempenho"
    },
    "REPORT": {
        "step": "report",
        "position": 5,
        "description": "Relatório Final"
    },
    "WORKSHOP": {
        "step": "workshop",
        "position": 6,
        "description": "Seminário"
    },
    "COMPLETED": {
        "step": "completed",
        "position": 7,
        "description": "Concluído"
    }
}
